decodes/__init__.py
decodes/core/__init__.py
decodes/core/dc_base.py
decodes/core/dc_bounds.py
decodes/core/dc_circle.py
decodes/core/dc_color.py
decodes/core/dc_cone.py
decodes/core/dc_cs.py
decodes/core/dc_curve.py
decodes/core/dc_cylinder.py
decodes/core/dc_graph.py
decodes/core/dc_grid.py
decodes/core/dc_has_pts.py
decodes/core/dc_intersection.py
decodes/core/dc_interval.py
decodes/core/dc_line.py
decodes/core/dc_mesh.py
decodes/core/dc_pgon.py
decodes/core/dc_plane.py
decodes/core/dc_pline.py
decodes/core/dc_point.py
decodes/core/dc_raster.py
decodes/core/dc_surface.py
decodes/core/dc_tri.py
decodes/core/dc_vec.py
decodes/core/dc_xform.py
decodes/extensions/__init__.py
decodes/extensions/cellular_automata.py
decodes/extensions/classical_surfaces.py
decodes/extensions/lsystem.py
decodes/extensions/packing.py
decodes/extensions/parse_epw.py
decodes/extensions/poisson_sampling.py
decodes/extensions/reaction_diffusion.py
decodes/extensions/solar_geometry.py
decodes/extensions/tiling_2d.py
decodes/extensions/tiling_danzer.py
decodes/extensions/voxel.py
decodes/io/__init__.py
decodes/io/autocad_out.py
decodes/io/dynamo_in.py
decodes/io/dynamo_out.py
decodes/io/gh_in.py
decodes/io/gh_out.py
decodes/io/json_out.py
decodes/io/jupyter_out.py
decodes/io/outie.py
decodes/io/processing_out.py
decodes/io/rhino_in.py
decodes/io/rhino_out.py
decodes/io/svg_out.py
decodes/io/threejs_out.py
decodes/io/jsonpickle/__init__.py
decodes/io/jsonpickle/_samples.py
decodes/io/jsonpickle/backend.py
decodes/io/jsonpickle/compat.py
decodes/io/jsonpickle/handlers.py
decodes/io/jsonpickle/pickler.py
decodes/io/jsonpickle/tags.py
decodes/io/jsonpickle/unpickler.py
decodes/io/jsonpickle/util.py
decodes/io/jsonpickle/version.py
decodes/io/pyautocad/__init__.py
decodes/io/pyautocad/api.py
decodes/io/pyautocad/cache.py
decodes/io/pyautocad/types.py
decodes/io/pyautocad/utils.py
decodes/io/pyautocad/contrib/__init__.py
decodes-0.2.3.dist-info/DESCRIPTION.rst
decodes-0.2.3.dist-info/LICENSE.txt
decodes-0.2.3.dist-info/METADATA
decodes-0.2.3.dist-info/RECORD
decodes-0.2.3.dist-info/WHEEL
decodes-0.2.3.dist-info/metadata.json
decodes-0.2.3.dist-info/top_level.txt
